poetry_dummy_greeting/__init__.py
poetry_dummy_greeting/greeting.py
poetry_dummy_greeting-0.1.0.dist-info/METADATA
poetry_dummy_greeting-0.1.0.dist-info/WHEEL
poetry_dummy_greeting-0.1.0.dist-info/RECORD
