Metadata-Version: 2.1
Name: poetry-dummy-greeting
Version: 0.1.0
Summary: 
Author: Angshuman Paul
Author-email: paulang1807@gmail.com
Requires-Python: >=3.9,<4.0
Classifier: Programming Language :: Python :: 3
Classifier: Programming Language :: Python :: 3.9
Classifier: Programming Language :: Python :: 3.10
Classifier: Programming Language :: Python :: 3.11
Classifier: Programming Language :: Python :: 3.12
